editor/__init__.py
editor/cmdline.py
editor/common.py
editor/daemon/__init__.py
editor/daemon/mac.py
editor/daemon/termux.py
editor/daemon/utils.py
editor/static/index.html
editor/static/logo.svg
editor/static/assets/index-Gt6ZQ-uZ.css
editor/static/assets/index-p_W-uX3v.js
editor/static/assets/logo-IgEysxkL.svg
editor/static/assets/source_sans-HsFb1qe3.woff
webvim-0.3.13.dist-info/METADATA
webvim-0.3.13.dist-info/WHEEL
webvim-0.3.13.dist-info/entry_points.txt
webvim-0.3.13.dist-info/top_level.txt
webvim-0.3.13.dist-info/RECORD
